h2o_experiment_tracking/exception.cpython-38-x86_64-linux-gnu.so
h2o_experiment_tracking/__init__.cpython-38-x86_64-linux-gnu.so
h2o_experiment_tracking/cli.cpython-38-x86_64-linux-gnu.so
h2o_experiment_tracking/context.cpython-38-x86_64-linux-gnu.so
h2o_experiment_tracking/config.cpython-38-x86_64-linux-gnu.so
h2o_experiment_tracking/constants.cpython-38-x86_64-linux-gnu.so
h2o_experiment_tracking/entities/iteration.cpython-38-x86_64-linux-gnu.so
h2o_experiment_tracking/entities/project.cpython-38-x86_64-linux-gnu.so
h2o_experiment_tracking/entities/named_entity.cpython-38-x86_64-linux-gnu.so
h2o_experiment_tracking/entities/experiment.cpython-38-x86_64-linux-gnu.so
h2o_experiment_tracking/entities/__init__.cpython-38-x86_64-linux-gnu.so
h2o_experiment_tracking/tracking/initialize.cpython-38-x86_64-linux-gnu.so
h2o_experiment_tracking/tracking/__init__.cpython-38-x86_64-linux-gnu.so
h2o_experiment_tracking/tracking/client.cpython-38-x86_64-linux-gnu.so
h2o_experiment_tracking/build_info/__init__.c
h2o_experiment_tracking/build_info/BUILD_INFO.txt
h2o_experiment_tracking/build_info/__init__.py
h2o_experiment_tracking/build_info/__init__.cpython-38-x86_64-linux-gnu.so
h2o_experiment_tracking/notebook/__init__.cpython-38-x86_64-linux-gnu.so
h2o_experiment_tracking/auth/user.cpython-38-x86_64-linux-gnu.so
h2o_experiment_tracking/auth/authenticator.cpython-38-x86_64-linux-gnu.so
h2o_experiment_tracking/auth/utils.cpython-38-x86_64-linux-gnu.so
h2o_experiment_tracking/auth/__init__.cpython-38-x86_64-linux-gnu.so
h2o_experiment_tracking/auth/lookup.cpython-38-x86_64-linux-gnu.so
h2o_experiment_tracking/utils/validation.cpython-38-x86_64-linux-gnu.so
h2o_experiment_tracking/utils/__init__.cpython-38-x86_64-linux-gnu.so
h2o_experiment_tracking/model/tags.cpython-38-x86_64-linux-gnu.so
h2o_experiment_tracking/model/__init__.cpython-38-x86_64-linux-gnu.so
h2o_experiment_tracking-0.0.4.dist-info/LICENSE
h2o_experiment_tracking-0.0.4.dist-info/entry_points.txt
h2o_experiment_tracking-0.0.4.dist-info/WHEEL
h2o_experiment_tracking-0.0.4.dist-info/METADATA
h2o_experiment_tracking-0.0.4.dist-info/top_level.txt
h2o_experiment_tracking-0.0.4.dist-info/RECORD
